<SliderSetInfo>
    <SliderSet name="CBBE BODY HDT - cuffsLeatherLegs">
        <SetFolder>CBBE BODY HDT - cuffsLeatherLegs</SetFolder>
        <SourceFile>CBBE BODY HDT - cuffsLeatherLegs.nif</SourceFile>
        <OutputPath>meshes\devious\devices</OutputPath>
        <OutputFile>cuffsLeatherLegs</OutputFile>
        <BaseShapeName target="cuffsLeatherLegs1">cuffsLeatherLegs1</BaseShapeName>
        <BaseShapeName target="cuffsLeatherLegs2">cuffsLeatherLegs2</BaseShapeName>
        <Slider name="PregnancyBelly" invert="false" small="0" big="0">
            <datafile name="cuffsLeatherLegs1PregnancyBelly" target="cuffsLeatherLegs1" local="true">cuffsLeatherLegs1PregnancyBelly.bsd</datafile>
            <datafile name="cuffsLeatherLegs2PregnancyBelly" target="cuffsLeatherLegs2" local="true">cuffsLeatherLegs2PregnancyBelly.bsd</datafile>
        </Slider>
        <Slider name="Butt" invert="true" small="0" big="100">
            <datafile name="cuffsLeatherLegs1Butt" target="cuffsLeatherLegs1" local="true">cuffsLeatherLegs1Butt.bsd</datafile>
            <datafile name="cuffsLeatherLegs2Butt" target="cuffsLeatherLegs2" local="true">cuffsLeatherLegs2Butt.bsd</datafile>
        </Slider>
        <Slider name="ButtSmall" invert="true" small="100" big="100">
            <datafile name="cuffsLeatherLegs1ButtSmall" target="cuffsLeatherLegs1" local="true">cuffsLeatherLegs1ButtSmall.bsd</datafile>
            <datafile name="cuffsLeatherLegs2ButtSmall" target="cuffsLeatherLegs2" local="true">cuffsLeatherLegs2ButtSmall.bsd</datafile>
        </Slider>
        <Slider name="BigButt" invert="false" small="0" big="0">
            <datafile name="cuffsLeatherLegs1BigButt" target="cuffsLeatherLegs1" local="true">cuffsLeatherLegs1BigButt.bsd</datafile>
            <datafile name="cuffsLeatherLegs2BigButt" target="cuffsLeatherLegs2" local="true">cuffsLeatherLegs2BigButt.bsd</datafile>
        </Slider>
        <Slider name="ChubbyButt" invert="false" small="0" big="0">
            <datafile name="cuffsLeatherLegs1ChubbyButt" target="cuffsLeatherLegs1" local="true">cuffsLeatherLegs1ChubbyButt.bsd</datafile>
            <datafile name="cuffsLeatherLegs2ChubbyButt" target="cuffsLeatherLegs2" local="true">cuffsLeatherLegs2ChubbyButt.bsd</datafile>
        </Slider>
        <Slider name="SlimThighs" invert="false" small="0" big="0">
            <datafile name="cuffsLeatherLegs1SlimThighs" target="cuffsLeatherLegs1" local="true">cuffsLeatherLegs1SlimThighs.bsd</datafile>
            <datafile name="cuffsLeatherLegs2SlimThighs" target="cuffsLeatherLegs2" local="true">cuffsLeatherLegs2SlimThighs.bsd</datafile>
        </Slider>
        <Slider name="Thighs" invert="false" small="0" big="0">
            <datafile name="cuffsLeatherLegs1Thighs" target="cuffsLeatherLegs1" local="true">cuffsLeatherLegs1Thighs.bsd</datafile>
            <datafile name="cuffsLeatherLegs2Thighs" target="cuffsLeatherLegs2" local="true">cuffsLeatherLegs2Thighs.bsd</datafile>
        </Slider>
        <Slider name="ChubbyLegs" invert="false" small="0" big="0">
            <datafile name="cuffsLeatherLegs1ChubbyLegs" target="cuffsLeatherLegs1" local="true">cuffsLeatherLegs1ChubbyLegs.bsd</datafile>
            <datafile name="cuffsLeatherLegs2ChubbyLegs" target="cuffsLeatherLegs2" local="true">cuffsLeatherLegs2ChubbyLegs.bsd</datafile>
        </Slider>
        <Slider name="Legs" invert="true" small="0" big="100">
            <datafile name="cuffsLeatherLegs1Legs" target="cuffsLeatherLegs1" local="true">cuffsLeatherLegs1Legs.bsd</datafile>
            <datafile name="cuffsLeatherLegs2Legs" target="cuffsLeatherLegs2" local="true">cuffsLeatherLegs2Legs.bsd</datafile>
        </Slider>
        <Slider name="KneeHeight" invert="false" small="0" big="0">
            <datafile name="cuffsLeatherLegs1KneeHeight" target="cuffsLeatherLegs1" local="true">cuffsLeatherLegs1KneeHeight.bsd</datafile>
            <datafile name="cuffsLeatherLegs2KneeHeight" target="cuffsLeatherLegs2" local="true">cuffsLeatherLegs2KneeHeight.bsd</datafile>
        </Slider>
        <Slider name="CalfSize" invert="false" small="0" big="0">
            <datafile name="cuffsLeatherLegs1CalfSize" target="cuffsLeatherLegs1" local="true">cuffsLeatherLegs1CalfSize.bsd</datafile>
            <datafile name="cuffsLeatherLegs2CalfSize" target="cuffsLeatherLegs2" local="true">cuffsLeatherLegs2CalfSize.bsd</datafile>
        </Slider>
        <Slider name="CalfSmooth" invert="false" small="0" big="0">
            <datafile name="cuffsLeatherLegs1CalfSmooth" target="cuffsLeatherLegs1" local="true">cuffsLeatherLegs1CalfSmooth.bsd</datafile>
            <datafile name="cuffsLeatherLegs2CalfSmooth" target="cuffsLeatherLegs2" local="true">cuffsLeatherLegs2CalfSmooth.bsd</datafile>
        </Slider>
        <Slider name="Ankles" invert="true" small="100" big="100">
            <datafile name="cuffsLeatherLegs1Ankles" target="cuffsLeatherLegs1" local="true">cuffsLeatherLegs1Ankles.bsd</datafile>
            <datafile name="cuffsLeatherLegs2Ankles" target="cuffsLeatherLegs2" local="true">cuffsLeatherLegs2Ankles.bsd</datafile>
        </Slider>
        <Slider name="SmallSeam" invert="false" small="100" big="0" hidden="true">
            <datafile name="cuffsLeatherLegs1SmallSeam" target="cuffsLeatherLegs1" local="true">cuffsLeatherLegs1SmallSeam.bsd</datafile>
            <datafile name="cuffsLeatherLegs2SmallSeam" target="cuffsLeatherLegs2" local="true">cuffsLeatherLegs2SmallSeam.bsd</datafile>
        </Slider>
    </SliderSet>
</SliderSetInfo>
